qcfractalcompute/__init__.py
qcfractalcompute/compress.py
qcfractalcompute/compute_manager.py
qcfractalcompute/compute_manager_cli.py
qcfractalcompute/config.py
qcfractalcompute/executors.py
qcfractalcompute/generic_wrapper.py
qcfractalcompute/process_targets.py
qcfractalcompute/test_compute_manager.py
qcfractalcompute/test_manager_config.py
qcfractalcompute/testing_helpers.py
qcfractalcompute/apps/__init__.py
qcfractalcompute/apps/app_manager.py
qcfractalcompute/apps/geometric.py
qcfractalcompute/apps/helpers.py
qcfractalcompute/apps/models.py
qcfractalcompute/apps/qcengine.py
qcfractalcompute/run_scripts/__init__.py
qcfractalcompute/run_scripts/conda_list_env.sh
qcfractalcompute/run_scripts/generic_script.py
qcfractalcompute/run_scripts/geometric_nextchain.py
qcfractalcompute/run_scripts/qcengine_compute.py
qcfractalcompute/run_scripts/qcengine_list.py
qcfractalcompute-0.63.dist-info/licenses/LICENSE
qcfractalcompute-0.63.dist-info/METADATA
qcfractalcompute-0.63.dist-info/WHEEL
qcfractalcompute-0.63.dist-info/entry_points.txt
qcfractalcompute-0.63.dist-info/top_level.txt
qcfractalcompute-0.63.dist-info/RECORD
